oneface/__init__.py
oneface/check.py
oneface/core.py
oneface/qt.py
oneface/utils.py
oneface/dash_app/__init__.py
oneface/dash_app/app.py
oneface/dash_app/embed.py
oneface/dash_app/input_item.py
oneface/wrap_cli/__init__.py
oneface/wrap_cli/__main__.py
oneface/wrap_cli/example.yaml
oneface/wrap_cli/wrap.py
oneFace-0.2.2.dist-info/LICENSE
oneFace-0.2.2.dist-info/METADATA
oneFace-0.2.2.dist-info/WHEEL
oneFace-0.2.2.dist-info/top_level.txt
oneFace-0.2.2.dist-info/RECORD
