Metadata-Version: 2.1
Name: oneFace
Version: 0.2.2
Summary: oneFace is a library for automatically generating multiple interfaces(CLI, GUI) from a callable Python object
Home-page: https://github.com/Nanguage/oneFace
Author: Weize Xu
Author-email: vet.xwz@gmail.com
License: MIT
Keywords: GUI,CLI
Classifier: Development Status :: 3 - Alpha
Classifier: Operating System :: OS Independent
Classifier: Programming Language :: Python
Classifier: Programming Language :: Python :: 3
Classifier: Programming Language :: Python :: 3.8
Classifier: Programming Language :: Python :: 3.9
Classifier: Programming Language :: Python :: 3.10
Classifier: License :: OSI Approved :: MIT License
Classifier: Intended Audience :: Science/Research
Classifier: Intended Audience :: Developers
Requires-Python: >=3.8, <4
License-File: LICENSE
Requires-Dist: funcdesc (>=0.1.2)
Requires-Dist: cmd2func (>=0.1.4)
Requires-Dist: rich
Requires-Dist: fire
Requires-Dist: qtpy
Requires-Dist: pyYAML
Provides-Extra: all
Requires-Dist: pyqt6 ; extra == 'all'
Requires-Dist: ansi2html ; extra == 'all'
Requires-Dist: dash ; extra == 'all'
Requires-Dist: visdcc ; extra == 'all'
Provides-Extra: dash
Requires-Dist: ansi2html ; extra == 'dash'
Requires-Dist: dash ; extra == 'dash'
Requires-Dist: visdcc ; extra == 'dash'
Provides-Extra: dev
Requires-Dist: pytest ; extra == 'dev'
Requires-Dist: pytest-cov ; extra == 'dev'
Requires-Dist: flake8 ; extra == 'dev'
Requires-Dist: mkdocs ; extra == 'dev'
Requires-Dist: mkdocs-material ; extra == 'dev'
Provides-Extra: doc
Requires-Dist: mkdocs ; extra == 'doc'
Requires-Dist: mkdocs-material ; extra == 'doc'
Provides-Extra: pyqt5
Requires-Dist: pyqt5 ; extra == 'pyqt5'
Provides-Extra: pyqt6
Requires-Dist: pyqt6 ; extra == 'pyqt6'
Provides-Extra: pyside2
Requires-Dist: PySide2 ; extra == 'pyside2'
Provides-Extra: pyside6
Requires-Dist: PySide6 ; extra == 'pyside6'
Provides-Extra: qt
Requires-Dist: pyqt6 ; extra == 'qt'
Provides-Extra: test
Requires-Dist: pytest ; extra == 'test'
Requires-Dist: pytest-cov ; extra == 'test'
Requires-Dist: flake8 ; extra == 'test'
